{{"dname": "IU酒店", "qname": "IU酒店", "group": "cheap", "groupType": "经济型", "hotDegree": "0"},
{"dname": "百时快捷酒店", "qname": "百时快捷酒店", "group": "cheap", "groupType": "经济型", "hotDegree": "0"},
{"dname": "铂尔曼", "qname": "铂尔曼", "group": "higher", "groupType": "豪华型", "hotDegree": "0"},
{"dname": "布丁酒店", "qname": "布丁酒店", "group": "cheap", "groupType": "经济型", "hotDegree": "0"},
{"dname": "登巴国际连锁客栈", "qname": "登巴国际连锁客栈", "group": "cheap", "groupType": "经济型", "hotDegree": "0"},
{"dname": "福朋喜来登", "qname": "福朋喜来登", "group": "normal", "groupType": "高档型", "hotDegree": "0"},
{"dname": "格兰云天国际", "qname": "格兰云天国际", "group": "higher", "groupType": "豪华型", "hotDegree": "0"},
{"dname": "格林豪泰酒店", "qname": "格林豪泰酒店", "group": "cheap", "groupType": "经济型", "hotDegree": "0"},
{"dname": "国际青年旅舍", "qname": "国际青年旅舍", "group": "cheap", "groupType": "经济型", "hotDegree": "0"},
{"dname": "汉庭酒店", "qname": "汉庭酒店", "group": "cheap", "groupType": "经济型", "hotDegree": "0"},
{"dname": "豪生", "qname": "豪生", "group": "higher", "groupType": "豪华型", "hotDegree": "0"},
{"dname": "锦江酒店", "qname": "锦江酒店", "group": "normal", "groupType": "高档型", "hotDegree": "0"},
{"dname": "凯宾斯基", "qname": "凯宾斯基", "group": "higher", "groupType": "豪华型", "hotDegree": "0"},
{"dname": "莫泰酒店", "qname": "莫泰酒店", "group": "cheap", "groupType": "经济型", "hotDegree": "0"},
{"dname": "诺富特", "qname": "诺富特", "group": "normal", "groupType": "高档型", "hotDegree": "0"},
{"dname": "7天酒店", "qname": "7天酒店", "group": "cheap", "groupType": "经济型", "hotDegree": "0"},
{"dname": "派酒店", "qname": "派酒店", "group": "cheap", "groupType": "经济型", "hotDegree": "0"},
{"dname": "如家快捷酒店", "qname": "如家快捷酒店", "group": "cheap", "groupType": "经济型", "hotDegree": "0"},
{"dname": "世纪金源", "qname": "世纪金源", "group": "higher", "groupType": "豪华型", "hotDegree": "0"},
{"dname": "索菲特", "qname": "索菲特", "group": "higher", "groupType": "豪华型", "hotDegree": "0"},
{"dname": "万丽", "qname": "万丽", "group": "higher", "groupType": "豪华型", "hotDegree": "0"},
{"dname": "维也纳酒店", "qname": "维也纳酒店", "group": "comfortable", "groupType": "舒适型", "hotDegree": "0"},
{"dname": "喜来登", "qname": "喜来登", "group": "higher", "groupType": "豪华型", "hotDegree": "0"},
{"dname": "星程酒店", "qname": "星程酒店", "group": "comfortable", "groupType": "舒适型", "hotDegree": "0"},
{"dname": "新世界", "qname": "新世界", "group": "higher", "groupType": "豪华型", "hotDegree": "0"},
{"dname": "速8酒店", "qname": "速8酒店", "group": "cheap", "groupType": "经济型", "hotDegree": "0"},
{"dname": "锦江之星酒店", "qname": "锦江之星酒店", "group": "cheap", "groupType": "经济型", "hotDegree": "0"},
{"dname": "HyattRegency", "qname": "HyattRegency", "group": "higher", "groupType": "豪华型", "hotDegree": "0"},
{"dname": "尚客优连锁酒店", "qname": "尚客优连锁酒店", "group": "cheap", "groupType": "经济型", "hotDegree": "0"},
}