{{"dname": "阪急", "qname": "阪急", "group": "comfortable", "groupType": "舒适型", "hotDegree": "0"},
{"dname": "岐山", "qname": "岐山", "group": "comfortable", "groupType": "舒适型", "hotDegree": "0"},
{"dname": "东急", "qname": "东急", "group": "comfortable", "groupType": "舒适型", "hotDegree": "0"},
{"dname": "皇冠假日", "qname": "皇冠假日", "group": "higher", "groupType": "豪华型", "hotDegree": "0"},
{"dname": "凯富", "qname": "凯富", "group": "normal", "groupType": "高档型", "hotDegree": "0"},
{"dname": "美居", "qname": "美居", "group": "normal", "groupType": "高档型", "hotDegree": "0"},
{"dname": "东横酒店", "qname": "东横酒店", "group": "cheap", "groupType": "经济型", "hotDegree": "0"},
{"dname": "万豪", "qname": "万豪", "group": "higher", "groupType": "豪华型", "hotDegree": "0"},
{"dname": "威斯汀", "qname": "威斯汀", "group": "higher", "groupType": "豪华型", "hotDegree": "0"},
{"dname": "希尔顿", "qname": "希尔顿", "group": "higher", "groupType": "豪华型", "hotDegree": "0"},
{"dname": "贝斯特韦斯特", "qname": "贝斯特韦斯特", "group": "normal", "groupType": "高档型", "hotDegree": "0"},
}